{
  "project_info": {
    "project_number": "972569075106",
    "project_id": "calendarexpenseapp",
    "storage_bucket": "calendarexpenseapp.firebasestorage.app"
  },
  "client": [
    {
      "client_info": {
        "mobilesdk_app_id": "1:972569075106:android:3828931b1704c4788fe6fb",
        "android_client_info": {
          "package_name": "com.example.calendar_expense_app"
        }
      },
      "oauth_client": [],
      "api_key": [
        {
          "current_key": "AIzaSyBbe2rk4ycTRzxKiwTpGwfKRgYrnVN4U6A"
        }
      ],
      "services": {
        "appinvite_service": {
          "other_platform_oauth_client": []
        }
      }
    },
    {
      "client_info": {
        "mobilesdk_app_id": "1:972569075106:android:18f1bf18bb40dd938fe6fb",
        "android_client_info": {
          "package_name": "com.example.demo_app"
        }
      },
      "oauth_client": [],
      "api_key": [
        {
          "current_key": "AIzaSyBbe2rk4ycTRzxKiwTpGwfKRgYrnVN4U6A"
        }
      ],
      "services": {
        "appinvite_service": {
          "other_platform_oauth_client": []
        }
      }
    }
  ],
  "configuration_version": "1"
}